jason_server/__init__.py
jason_server/cli.py
jason_server/database.py
jason_server/derulo.py
jason_server/utils.py
jason_server/views/index.html
jason_server-0.8.1.dist-info/LICENSE
jason_server-0.8.1.dist-info/METADATA
jason_server-0.8.1.dist-info/WHEEL
jason_server-0.8.1.dist-info/entry_points.txt
jason_server-0.8.1.dist-info/top_level.txt
jason_server-0.8.1.dist-info/RECORD
