Metadata-Version: 2.1
Name: jason-server
Version: 0.8.1
Summary: JSON as REST API
Home-page: https://github.com/nekomamoushi/jason-server
Author: Jerome Pradier
Author-email: germione.grangere@gmail.com
License: MIT
Keywords: packaging setuptools development
Platform: UNKNOWN
Classifier: Development Status :: 4 - Beta
Classifier: Intended Audience :: Developers
Classifier: Topic :: Software Development :: Build Tools
Classifier: License :: OSI Approved :: MIT License
Classifier: Programming Language :: Python :: 2
Classifier: Programming Language :: Python :: 2.7
Classifier: Programming Language :: Python :: 3
Classifier: Programming Language :: Python :: 3.7
Requires-Dist: click
Requires-Dist: bottle
Requires-Dist: tinydb
